{
  "data": [
    {
      "id": "0",
      "date": "2024-04-13T21:00:00.000Z",
      "object": "адыгейск",
      "cost": 30000,
      "workDays": 3,
      "source": "Юра"
    },
    {
      "id": "1",
      "date": "2023-04-13T21:00:00.000Z",
      "object": "адыгейск",
      "cost": 30000,
      "workDays": 3,
      "source": "Юра"
    },
    {
      "id": "2",
      "date": "2024-05-13T21:00:00.000Z",
      "object": "адыbv",
      "cost": "4444",
      "workDays": 3,
      "source": "Юра"
    },
    {
      "id": "3",
      "date": "2024-05-13T21:00:00.000Z",
      "object": "адыге",
      "cost": "30000",
      "workDays": 3,
      "source": "Юра"
    },
    {
      "id": "4",
      "date": "2024-05-13T21:00:00.000Z",
      "object": "tttt",
      "cost": "30000",
      "workDays": 3,
      "source": "ttt"
    },
    {
      "id": "5",
      "object": "fff",
      "cost": "3336",
      "workDays": "434",
      "source": "43",
      "date": "2024-05-01T00:00:00.000Z"
    }
  ]
}